{
  "$schema" : "https://json-schema.axonivy.com/14.0-dev/project/data-class.json",
  "simpleName" : "FileUploadSimpleModeDemoData",
  "namespace" : "ch.ivyteam.htmldialog.demo.input.FileUploadSimpleModeDemo",
  "fields" : [ {
    "name" : "ivyFile",
    "type" : "File",
    "modifiers" : [ ]
  }, {
    "name" : "textContent",
    "modifiers" : [ ]
  }, {
    "name" : "filePath"
  }, {
    "name" : "fileName",
    "modifiers" : [ ]
  }, {
    "name" : "fileDownload",
    "type" : "org.primefaces.model.StreamedContent",
    "modifiers" : [ ]
  }, {
    "name" : "showContent",
    "type" : "Boolean"
  } ]
}