{
  "$schema" : "https://json-schema.axonivy.com/14.0-dev/project/data-class.json",
  "simpleName" : "DataMappingData",
  "namespace" : "com.axonivy.connectivity.rest",
  "fields" : [ {
    "name" : "myPost",
    "type" : "com.axonivy.connectivity.rest.Post",
    "modifiers" : [ ]
  }, {
    "name" : "userId",
    "type" : "Number",
    "modifiers" : [ ]
  }, {
    "name" : "posts",
    "type" : "java.util.List<com.axonivy.connectivity.rest.Post>",
    "modifiers" : [ ]
  }, {
    "name" : "user",
    "type" : "com.axonivy.connectivity.rest.User",
    "modifiers" : [ ]
  }, {
    "name" : "userGenerated",
    "type" : "com.typicode.jsonplaceholder.User",
    "modifiers" : [ ]
  } ]
}